LICENSE
MANIFEST.in
README.md
setup.cfg
setup.py
examples/dc-gap-sweep.py
examples/dc-sweep-soi-3db-index-profile-200nm-gap.png
examples/dc-sweep-soi-3db.png
examples/example1.py
examples/example2.py
examples/fraction_te.png
examples/fraction_tm.png
examples/gc-sweep-soi.png
examples/gc-sweep-soi.py
examples/width-sweep-soi.png
examples/width-sweep-soi.py
modesolverpy/__init__.py
modesolverpy/_analyse.py
modesolverpy/_mode_solver_lib.py
modesolverpy/coupling_efficiency.py
modesolverpy/design.py
modesolverpy/fractions.gpi
modesolverpy/mode.gpi
modesolverpy/mode_solver.py
modesolverpy/n_effs.gpi
modesolverpy/structure.gpi
modesolverpy/structure.py
modesolverpy/structure_base.py
modesolverpy.egg-info/PKG-INFO
modesolverpy.egg-info/SOURCES.txt
modesolverpy.egg-info/dependency_links.txt
modesolverpy.egg-info/not-zip-safe
modesolverpy.egg-info/requires.txt
modesolverpy.egg-info/top_level.txt