Metadata-Version: 1.0
Name: modesolverpy
Version: 0.4.4
Summary: Photonic mode solver.
Home-page: https://github.com/jtambasco/modesolverpy
Author: Jean-Luc Tambasco
Author-email: an.obscurity@gmail.com
License: MIT
Platform: UNKNOWN
